reqrio/__init__.py
reqrio/alpn.py
reqrio/bindings.py
reqrio/header.py
reqrio/method.py
reqrio/pool.py
reqrio/reqrio.dll
reqrio/response.py
reqrio/session.py
reqrio/stream.py
reqrio/websocket.py
reqrio/hooks/__init__.py
reqrio/hooks/hook-reqrio.py
reqrio-0.0.16.dist-info/METADATA
reqrio-0.0.16.dist-info/WHEEL
reqrio-0.0.16.dist-info/entry_points.txt
reqrio-0.0.16.dist-info/top_level.txt
reqrio-0.0.16.dist-info/RECORD
