Metadata-Version: 2.4
Name: reqrio
Version: 0.0.16
Summary: A http lib
Author-email: xllgl2017 <xinlanxi2017@gmail.com>
License-Expression: MIT
Project-URL: Homepage, https://github.com/xllgl2017/reqrio/tree/master/reqrio
Requires-Python: >=3.9
